[
  {
    "language": "c#",
    "projects": [
      "shadowsocks/shadowsocks-windows",
      "dotnet/roslyn",
      "MaterialDesignInXAML/MaterialDesignInXamlToolkit",
      "OpenRA/OpenRA",
      "lionsoul2014/ip2region",
      "mono/mono",
      "Ryujinx/Ryujinx",
      "Unity-Technologies/UnityCsReference",
      "dotnet/csharplang",
      "JeffreySu/WeiXinMPSDK",
      "JustArchiNET/ArchiSteamFarm",
      "QuantConnect/Lean",
      "sschmid/Entitas-CSharp",
      "unoplatform/uno",
      "bchavez/Bogus",
      "egametang/ET",
      "microsoft/FASTER",
      "aalhour/C-Sharp-Algorithms",
      "sta/websocket-sharp",
      "dotnet-state-machine/stateless"
    ]
  },
  {
    "language": "go",
    "projects": [
      "golang/go",
      "kubernetes/kubernetes",
      "avelino/awesome-go",
      "moby/moby",
      "gohugoio/hugo",
      "gin-gonic/gin",
      "fatedier/frp",
      "syncthing/syncthing",
      "astaxie/build-web-application-with-golang",
      "junegunn/fzf",
      "gogs/gogs",
      "etcd-io/etcd",
      "traefik/traefik",
      "caddyserver/caddy",
      "ethereum/go-ethereum",
      "minio/minio",
      "pingcap/tidb",
      "rclone/rclone",
      "beego/beego",
      "unknwon/the-way-to-go_ZH_CN"
    ]
  },
  {
    "language": "python",
    "projects": [
      "donnemartin/system-design-primer",
      "TheAlgorithms/Python",
      "jackfrued/Python-100-Days",
      "vinta/awesome-python",
      "nvbn/thefuck",
      "django/django",
      "pallets/flask",
      "keras-team/keras",
      "httpie/httpie",
      "ansible/ansible",
      "psf/requests",
      "521xueweihan/HelloGitHub",
      "home-assistant/core",
      "scrapy/scrapy",
      "ageitgey/face_recognition",
      "apache/superset",
      "python/cpython",
      "3b1b/manim",
      "tiangolo/fastapi",
      "fighting41love/funNLP"
    ]
  },
  {
    "language": "java",
    "projects": [
      "CyC2018/CS-Notes",
      "Snailclimb/JavaGuide",
      "iluwatar/java-design-patterns",
      "spring-projects/spring-boot",
      "elastic/elasticsearch",
      "doocs/advanced-java",
      "kdn251/interviews",
      "macrozheng/mall",
      "ReactiveX/RxJava",
      "google/guava",
      "square/okhttp",
      "TheAlgorithms/Java",
      "square/retrofit",
      "apache/dubbo",
      "PhilJay/MPAndroidChart",
      "zxing/zxing",
      "skylot/jadx",
      "alibaba/arthas",
      "crossoverJie/JCSprout",
      "ityouknow/spring-boot-examples"
    ]
  },
  {
    "language": "javascript",
    "projects": [
      "freeCodeCamp/freeCodeCamp",
      "vuejs/vue",
      "facebook/react",
      "twbs/bootstrap",
      "trekhleb/javascript-algorithms",
      "airbnb/javascript",
      "axios/axios",
      "30-seconds/30-seconds-of-code",
      "mrdoob/three.js",
      "mui-org/material-ui",
      "goldbergyoni/nodebestpractices",
      "webpack/webpack",
      "atom/atom",
      "jquery/jquery",
      "ryanmcdermott/clean-code-javascript",
      "chartjs/Chart.js",
      "expressjs/express",
      "h5bp/html5-boilerplate",
      "lodash/lodash"
    ]
  }
]